{
    "paragraph": " Zalta (ed.), URL = <https://plato.stanford.edu/archives/win2020/ entries/content-externalism/>. ADDITIONAL DISCUSSIONS Block, Ned. 1991. \u201cWhat Narrow Content Is Not.\u201d In B. Loewer and G. Rey (eds.) Meaning and Mind: Fodor and His Critics. Oxford: Blackwell: 33\u201364. Burge, Tyler. 1988. \u201cIndividualism and Self-Knowledge.\u201d Journal of Philosophy 85: 649\u201363. Burge, Tyler. 2007. \u201cPostscript to \u2018Individualism and the Mental\u2019\u201d. In his Founda- tions of Mind. New York: Oxford University Press: 151\u201381. Fodor, Jerry A. 1987. Psychosemantics: The Problem of Meaning in the Philosophy of Mind. Cambridge, MA: MIT Press. Georgalis, Nicholas 1999. \u201cRethinking Burge\u2019s Thought Experiment.\u201d Synthese 118 (2): 145\u201364. Gertler, Brie. 2012. \u201cUnderstanding the Internalism\u2013Externalism Debate: What Is the Boundary of the Thinker?\u201d Philosophical Perspectives 26 (1): 51\u201375. Pereboom, Derk. 1995. \u201cConceptual Structure and the Individuation of \u00adContent.\u201d Philosophical Perspectives 9: 401\u201326. Pessin, Andrew, and Goldberg, Sanford (eds.). 1996. The Twin Earth Chronicles: Twenty Years of Reflection on Hilary Putnam\u2019s \u201cThe Meaning of \u2018Meaning\u2019\u201d. \u00adArmonk, NY: Sharpe. Putnam, Hilary. 1975. \u201cThe Meaning of \u2018Meaning\u2019.\u201d In K. Gunderson (ed.) \u00adLanguage, Mind, and Knowledge: Minnesota Studies in the Philosophy of Science, Volume 7. Minneapolis: University of Minnesota Press: 139\u201393. Stalnaker, Robert. 1989. \u201cOn What\u2019s in the Head.\u201d Philosophical Perspectives 3: 287\u2013316. Stich, Stephen. 1983. From Folk Psychology to Cognitive Science: The Case Against Belief. Cambridge, MA: MIT Press. Yli-Vakkuri, Juhani, and Hawthorne, John. 2018. Narrow Content. Oxford: Oxford University Press. OTHER REFERENCES Alter, Torin. 2013. \u201cSocial Externalism and the Knowledge Argument.\u201d Mind 122: 481\u201396. Baker, Lynn R. 1987. Saving Belief: A Critique of Physicalism. Princeton: Princeton University Press. CONTENT, INTENTIONALITY, AND REPRESENTATION 160 Ball, Derek.",
    "metadata": "Philosophy of Mind_ 50 Puzzles, Paradoxes, and Thought Experiments by Torin Alter & Robert J",
    "question": "What is the main idea presented in Jerry Fodor's 1987 book \"Psychosemantics\"?",
    "answer": "The main idea presented in Jerry Fodor's 1987 book \"Psychosemantics\" is the problem of meaning in the philosophy of mind, specifically the idea that mental states have semantic properties that need to be explained.",
    "question_group_id": "a756828f-58ba-426f-905b-0287760da8c4",
    "paragraph_idx": 539,
    "question_idx": 1
}